{
  "form_id": "IRS8038CPScheduleA",
  "tax_year": 2023,
  "fields": [
    {
      "name": "BondIssueDt",
      "path": "BondIssueDt",
      "type": "date"
    },
    {
      "name": "EligibleInterestComputationGrp",
      "path": "EligibleInterestComputationGrp",
      "type": "group"
    },
    {
      "name": "ReportNum",
      "path": "ReportNum",
      "type": "string"
    },
    {
      "name": "TotalEligibleInterestCmptAmt",
      "path": "TotalEligibleInterestCmptAmt",
      "type": "usd"
    }
  ]
}